{"is_source_file": true, "format": "Dart", "description": "This file is the main entry point for a Flutter application, setting up the app and launching the widget tree.", "external_files": ["package:flutter/widgets.dart", "../src/app_entry.dart"], "external_methods": ["runApp"], "published": [], "classes": [{"name": "MyApp", "description": "The root widget of the Flutter application, likely extending StatelessWidget or StatefulWidget."}], "methods": [{"name": "main", "description": "Application entry point that initializes and runs the Flutter app."}], "calls": ["runApp"], "search-terms": ["main", "Flutter", "runApp", "MyApp", "entrypoint"], "state": 2, "file_id": 49, "knowledge_revision": 125, "git_revision": "", "hash": "b3a7e60aaecb270da349692af93b7be2", "format-version": 4, "code-base-name": "preference_frontend", "filename": "preference_frontend/lib/bin/main.dart", "revision_history": [{"125": ""}]}