{"is_source_file": true, "format": "Dart", "description": "This file implements a Flutter UI screen called FilterScreen, which includes filtering options such as height, weight, hair color, ethnicity, religion, with support for resetting, applying, and initial focus/navigation. It is composed of multiple nested widgets managing user interaction with filtering criteria.", "external_files": ["../models/filter_criteria.dart", "../state/filter_provider.dart", "../widgets/primary_button.dart", "package:flutter/material.dart", "package:provider/provider.dart"], "external_methods": ["Provider.of<FilterProvider>(context, listen: false)", "context.read<FilterProvider>()", "context.watch<FilterProvider>()", "ScrollController.ensureVisible()", "Navigator.of(context).maybePop()", "ScaffoldMessenger.of(context).showSnackBar()"], "published": ["FilterScreen", "FilterSection"], "classes": [{"name": "FilterScreen", "description": "A stateless widget that provides a filter UI screen with options and actions."}, {"name": "_FilterBody", "description": "A stateful widget managing the dynamic content of filter options, scrolling to initial section, and containing filter sections."}, {"name": "_FilterBodyState", "description": "State object for _FilterBody managing filter option states, scrolling, and animations."}, {"name": "_AnimatedSectionCard", "description": "A widget that adds a pulsing animation highlight to a section when activated."}, {"name": "_SectionCard", "description": "A container widget for each filter section, including header, helper text, and child content."}, {"name": "_SectionHeader", "description": "A widget displaying the section title and icon, optionally with a trailing range chip."}, {"name": "_HeaderChip", "description": "A styled label used in headers to display current range or status."}], "methods": [{"name": "_onReset", "description": "Resets the filters via provider and shows a snackbar confirmation."}, {"name": "_onResetLocal", "description": "Resets the local filter state copies and shows a snackbar."}, {"name": "_enumLabel", "description": "Converts enum name strings to human-readable labels."}], "calls": ["Provider.of<FilterProvider>(context, listen: false)", "context.read<FilterProvider>()", "context.watch<FilterProvider>()", "Scrollable.ensureVisible()", "Navigator.of(btnContext).maybePop()", "ScaffoldMessenger.of(context).showSnackBar()"], "search-terms": ["FilterScreen class", "filter options", "height range slider", "initial focus section", "filter reset", "deep-link navigation", "pulsing highlight", "enum checkbox group", "filter provider", "Flutter UI filter screen"], "state": 2, "file_id": 37, "knowledge_revision": 182, "git_revision": "", "revision_history": [{"113": ""}, {"132": ""}, {"137": ""}, {"139": ""}, {"146": ""}, {"149": ""}, {"151": ""}, {"178": ""}, {"182": ""}], "hash": "3d515f9054a8166977af8207757c51f9", "format-version": 4, "code-base-name": "preference_frontend", "filename": "preference_frontend/lib/screens/filter_screen.dart"}