{"is_source_file": true, "format": "Dart", "description": "This Dart source file defines the FilterProvider class, which manages filter criteria for a Flutter application. It provides getters, setters, toggle methods, and reset functionality for filter criteria such as hair colors, races, religions, height, and weight ranges, notifying listeners of changes.", "external_files": ["../models/filter_criteria.dart"], "external_methods": [], "published": ["criteria", "setCriteria", "toggleHairColor", "toggleRace", "toggleReligion", "updateHeightRange", "updateWeightRange", "reset", "apply", "hairColors", "races", "religions", "heightRange", "weightRange"], "classes": [{"name": "FilterProvider", "description": "A ChangeNotifier-based provider class managing filter criteria state and providing methods to modify and reset filters."}], "methods": [{"name": "setCriteria", "description": "Replaces the current filter criteria with a new one and notifies listeners."}, {"name": "toggleHairColor", "description": "Toggles the presence of a HairColor in the hairColors set, or sets it explicitly."}, {"name": "toggleRace", "description": "Toggles the presence of a Race in the races set, or sets it explicitly."}, {"name": "toggleReligion", "description": "Toggles the presence of a Religion in the religions set, or sets it explicitly."}, {"name": "updateHeightRange", "description": "Updates the height range filter."}, {"name": "updateWeightRange", "description": "Updates the weight range filter."}, {"name": "reset", "description": "Resets all filter criteria to default values."}, {"name": "apply", "description": "Placeholder method to trigger any matching refresh, currently only notifies listeners."}], "calls": ["notifyListeners", "Set.from", "copyWith"], "search-terms": ["FilterProvider", "filter criteria", "toggleHairColor", "toggleRace", "toggleReligion", "range", "heightRange", "weightRange", "flutter provider", "ChangeNotifier"], "state": 2, "file_id": 36, "knowledge_revision": 145, "git_revision": "", "revision_history": [{"112": ""}, {"131": ""}, {"136": ""}, {"140": ""}, {"143": ""}, {"145": ""}], "hash": "c8af271e9567b26dff74f5627bb4ee89", "format-version": 4, "code-base-name": "preference_frontend", "filename": "preference_frontend/lib/state/filter_provider.dart"}